expr_codegen/__init__.py
expr_codegen/_version.py
expr_codegen/codes.py
expr_codegen/dag.py
expr_codegen/expr.py
expr_codegen/model.py
expr_codegen/tool.py
expr_codegen/latex/__init__.py
expr_codegen/latex/printer.py
expr_codegen/pandas/__init__.py
expr_codegen/pandas/code.py
expr_codegen/pandas/helper.py
expr_codegen/pandas/printer.py
expr_codegen/pandas/ta.py
expr_codegen/pandas/template.py.j2
expr_codegen/polars/__init__.py
expr_codegen/polars/code.py
expr_codegen/polars/printer.py
expr_codegen/polars/template.py.j2
expr_codegen/rust/__init__.py
expr_codegen/rust/code.py
expr_codegen/rust/printer.py
expr_codegen/rust/template.rs.j2
expr_codegen/sql/__init__.py
expr_codegen/sql/code.py
expr_codegen/sql/printer.py
expr_codegen/sql/template.sql.j2
expr_codegen-0.16.3.dist-info/METADATA
expr_codegen-0.16.3.dist-info/WHEEL
expr_codegen-0.16.3.dist-info/licenses/LICENSE
expr_codegen-0.16.3.dist-info/RECORD
