Metadata-Version: 2.4
Name: expr_codegen
Version: 0.16.3
Summary: symbol expression to polars expression tool
Author-email: wukan <wu-kan@163.com>
License: BSD 3-Clause License
License-File: LICENSE
Keywords: expression,polars,talib
Classifier: Development Status :: 4 - Beta
Classifier: Programming Language :: Python
Requires-Python: >=3.9
Requires-Dist: ast-comments
Requires-Dist: black
Requires-Dist: jinja2
Requires-Dist: loguru
Requires-Dist: networkx
Requires-Dist: sympy
Provides-Extra: streamlit
Requires-Dist: more-itertools; extra == 'streamlit'
Requires-Dist: streamlit; extra == 'streamlit'
Requires-Dist: streamlit-ace; extra == 'streamlit'
